[
  {
    "id": "bebidas",
    "source": "bebidas.png",
    "slug": "bebidas",
    "original": {
      "width": 320,
      "height": 320,
      "bytes": 121203
    },
    "files": {
      "32": "32/bebidas.webp",
      "64": "64/bebidas.webp",
      "128": "128/bebidas.webp",
      "512": "512/bebidas.webp"
    },
    "bytes": {
      "32": 1114,
      "64": 2366,
      "128": 5352,
      "512": 36170
    }
  },
  {
    "id": "cafe",
    "source": "cafe.png",
    "slug": "cafe",
    "original": {
      "width": 320,
      "height": 320,
      "bytes": 111148
    },
    "files": {
      "32": "32/cafe.webp",
      "64": "64/cafe.webp",
      "128": "128/cafe.webp",
      "512": "512/cafe.webp"
    },
    "bytes": {
      "32": 1004,
      "64": 2346,
      "128": 5192,
      "512": 24076
    }
  },
  {
    "id": "desayuno",
    "source": "desayuno.png",
    "slug": "desayuno",
    "original": {
      "width": 320,
      "height": 320,
      "bytes": 133020
    },
    "files": {
      "32": "32/desayuno.webp",
      "64": "64/desayuno.webp",
      "128": "128/desayuno.webp",
      "512": "512/desayuno.webp"
    },
    "bytes": {
      "32": 1024,
      "64": 2438,
      "128": 6464,
      "512": 46422
    }
  },
  {
    "id": "ensalada",
    "source": "ensalada.png",
    "slug": "ensalada",
    "original": {
      "width": 320,
      "height": 320,
      "bytes": 132168
    },
    "files": {
      "32": "32/ensalada.webp",
      "64": "64/ensalada.webp",
      "128": "128/ensalada.webp",
      "512": "512/ensalada.webp"
    },
    "bytes": {
      "32": 1106,
      "64": 2486,
      "128": 5620,
      "512": 33468
    }
  },
  {
    "id": "hamburguesa",
    "source": "hamburguesa.png",
    "slug": "hamburguesa",
    "original": {
      "width": 320,
      "height": 320,
      "bytes": 190240
    },
    "files": {
      "32": "32/hamburguesa.webp",
      "64": "64/hamburguesa.webp",
      "128": "128/hamburguesa.webp",
      "512": "512/hamburguesa.webp"
    },
    "bytes": {
      "32": 1212,
      "64": 3130,
      "128": 8034,
      "512": 56426
    }
  },
  {
    "id": "pizza",
    "source": "pizza.png",
    "slug": "pizza",
    "original": {
      "width": 320,
      "height": 320,
      "bytes": 153836
    },
    "files": {
      "32": "32/pizza.webp",
      "64": "64/pizza.webp",
      "128": "128/pizza.webp",
      "512": "512/pizza.webp"
    },
    "bytes": {
      "32": 1228,
      "64": 2892,
      "128": 7114,
      "512": 47064
    }
  },
  {
    "id": "postres",
    "source": "postres.png",
    "slug": "postres",
    "original": {
      "width": 320,
      "height": 320,
      "bytes": 140342
    },
    "files": {
      "32": "32/postres.webp",
      "64": "64/postres.webp",
      "128": "128/postres.webp",
      "512": "512/postres.webp"
    },
    "bytes": {
      "32": 1134,
      "64": 2612,
      "128": 5894,
      "512": 32708
    }
  },
  {
    "id": "snacks",
    "source": "snacks.png",
    "slug": "snacks",
    "original": {
      "width": 320,
      "height": 320,
      "bytes": 159620
    },
    "files": {
      "32": "32/snacks.webp",
      "64": "64/snacks.webp",
      "128": "128/snacks.webp",
      "512": "512/snacks.webp"
    },
    "bytes": {
      "32": 1320,
      "64": 3420,
      "128": 9440,
      "512": 60950
    }
  },
  {
    "id": "sushi",
    "source": "sushi.png",
    "slug": "sushi",
    "original": {
      "width": 320,
      "height": 320,
      "bytes": 166516
    },
    "files": {
      "32": "32/sushi.webp",
      "64": "64/sushi.webp",
      "128": "128/sushi.webp",
      "512": "512/sushi.webp"
    },
    "bytes": {
      "32": 1082,
      "64": 2442,
      "128": 6262,
      "512": 38714
    }
  },
  {
    "id": "taco",
    "source": "taco.png",
    "slug": "taco",
    "original": {
      "width": 320,
      "height": 320,
      "bytes": 154867
    },
    "files": {
      "32": "32/taco.webp",
      "64": "64/taco.webp",
      "128": "128/taco.webp",
      "512": "512/taco.webp"
    },
    "bytes": {
      "32": 1184,
      "64": 2778,
      "128": 6714,
      "512": 44460
    }
  }
]
